noaa_weather_hourly/__init__.py
noaa_weather_hourly/__main__.py
noaa_weather_hourly/config.py
noaa_weather_hourly/data/3876540.csv
noaa_weather_hourly/data/__init__.py
noaa_weather_hourly/data/isd-history.csv
noaa_weather_hourly/data/isd_history_defintions.txt
noaa_weather_hourly/data/LCD_documentation.pdf
noaa_weather_hourly/data/LCD_USW00014939_2020.csv
noaa_weather_hourly/ISD History Station Table.py
noaa_weather_hourly/tests/__init__.py
noaa_weather_hourly/utils.py
noaa_weather_hourly-1.0.3.dist-info/entry_points.txt
noaa_weather_hourly-1.0.3.dist-info/LICENSE
noaa_weather_hourly-1.0.3.dist-info/METADATA
noaa_weather_hourly-1.0.3.dist-info/WHEEL
noaa_weather_hourly-1.0.3.dist-info/RECORD
