Metadata-Version: 2.1
Name: noaa_weather_hourly
Version: 1.0.3
Summary: Cleans historical LCD weather files from NOAA and returns an hourly .CSV file
Home-page: https://github.com/emskiphoto/noaa_weather_hourly
License: Apache-2.0
Keywords: noaa,baseline-model,sunrise-times,noaa weather,8760,energy model calibration,sunset-times,weather normalization,historical weather data,weather files,hourly weather
Author: Matt Chmielewski
Requires-Python: >=3.8,<4.0
Classifier: License :: OSI Approved :: Apache Software License
Classifier: Programming Language :: Python
Classifier: Programming Language :: Python :: 3
Classifier: Programming Language :: Python :: 3.8
Classifier: Programming Language :: Python :: 3.9
Classifier: Programming Language :: Python :: 3.10
Classifier: Programming Language :: Python :: 3.11
Classifier: Programming Language :: Python :: 3.12
Classifier: Programming Language :: Python :: 3.13
Requires-Dist: numpy (>1.14.6,<=1.26.4)
Requires-Dist: pandas (>1.3.5,<=2.1.4)
Project-URL: Repository, https://github.com/emskiphoto/noaa_weather_hourly
